iliad/__init__.py
iliad/cli.py
iliad/find.py
iliad/py.typed
iliad/reprinter.py
iliad-0.5.1.dist-info/entry_points.txt
iliad-0.5.1.dist-info/LICENSE
iliad-0.5.1.dist-info/WHEEL
iliad-0.5.1.dist-info/METADATA
iliad-0.5.1.dist-info/RECORD
