Metadata-Version: 2.1
Name: iliad
Version: 0.5.1
Summary: A monorepo tool for Poetry
Home-page: https://github.com/eganjs/iliad
License: MIT
Author: Joseph Egan
Author-email: joseph.s.egan@gmail.com
Requires-Python: >=3.6,<4.0
Classifier: License :: OSI Approved :: MIT License
Classifier: Programming Language :: Python :: 3
Classifier: Programming Language :: Python :: 3.6
Classifier: Programming Language :: Python :: 3.7
Classifier: Programming Language :: Python :: 3.8
Classifier: Programming Language :: Python :: 3.9
Requires-Dist: click (>=7.1.2,<8.0.0)
Requires-Dist: tomlkit (>=0.7.0,<0.8.0)
Project-URL: Repository, https://github.com/eganjs/iliad
